Workbook

Sheet Brightline DCF Valuation
B3: x | C3: Revenue Forecast Model
C5: Periods | E5: 2023 | F5: 2024 | G5: 2025 | H5: 2026 | I5: 2027 | J5: 2028 | K5: 2029 | L5: 2030
C7: Ridership
C8: Short-Distance | E8: 1747762 | F8: 1135505 | G8: 1227198 | H8: =G8*(1+H34) -> 1448093.6 | I8: =H8*(1+I34) -> 1650826.7 | J8: =I8*(1+J34) -> 1824163.6 | K8: =J8*(1+K34) -> 1878888.5 | L8: =K8*(1+L34) -> 1935255.1
C9: Long-Distance | E9: 306131 | F9: 1628007 | G9: 1889125 | H9: =G9*(1+H35) -> 2078037.5 | I9: =H9*(1+I35) -> 2213109.9 | J9: =I9*(1+J35) -> 2301634.3 | K9: =J9*(1+K35) -> 2370683.4 | L9: =K9*(1+L35) -> 2441803.9
C10: Total | E10: =SUM(E9,E8) -> 2053893 | F10: =SUM(F9,F8) -> 2763512 | G10: =SUM(G9,G8) -> 3116323 | H10: =SUM(H8:H9) -> 3526131.1 | I10: =SUM(I8:I9) -> 3863936.7 | J10: =SUM(J8:J9) -> 4125797.9 | K10: =SUM(K8:K9) -> 4249571.8 | L10: =SUM(L8:L9) -> 4377059
C12: Average Fare per Passenger
C13: Short-Distance | E13: 22.31 | F13: 29.34 | G13: 26.1 | H13: =G13*(1+H38) -> 27.144 | I13: =H13*(1+I38) -> 27.95832 | J13: =I13*(1+J38) -> 28.517486 | K13: =J13*(1+K38) -> 28.802661 | L13: =K13*(1+L38) -> 29.090688
C14: Long-Distance | E14: 85.34 | F14: 73.2 | G14: 74.74 | H14: =G14*(1+H39) -> 76.2348 | I14: =H14*(1+I39) -> 77.759496 | J14: =I14*(1+J39) -> 78.537091 | K14: =J14*(1+K39) -> 79.715147 | L14: =K14*(1+L39) -> 80.910875
C16: Ticket Revenue
C17: Short-Distance | E17: =(E8*E13)/1000 -> 38992.57 | F17: =(F8*F13)/1000 -> 33315.717 | G17: =(G8*G13)/1000 -> 32029.868 | H17: =(H8*H13)/1000 -> 39307.054 | I17: =(I8*I13)/1000 -> 46154.343 | J17: =(J8*J13)/1000 -> 52020.559 | K17: =(K8*K13)/1000 -> 54116.988 | L17: =(L8*L13)/1000 -> 56297.903
C18: Long-Distance | E18: =(E9*E14)/1000 -> 26125.22 | F18: =(F9*F14)/1000 -> 119170.11 | G18: =(G9*G14)/1000 -> 141193.2 | H18: =(H9*H14)/1000 -> 158418.77 | I18: =(I9*I14)/1000 -> 172090.31 | J18: =(J9*J14)/1000 -> 180763.67 | K18: =(K9*K14)/1000 -> 188979.37 | L18: =(L9*L14)/1000 -> 197568.49
C19: Total | E19: =SUM(E17:E18) -> 65117.79 | F19: =SUM(F17:F18) -> 152485.83 | G19: =SUM(G17:G18) -> 173223.07 | H19: =SUM(H17:H18) -> 197725.83 | I19: =SUM(I17:I18) -> 218244.66 | J19: =SUM(J17:J18) -> 232784.22 | K19: =SUM(K17:K18) -> 243096.36 | L19: =SUM(L17:L18) -> 253866.39
C21: Passenger Food and Beverage | E21: 5917 | F21: 12495 | G21: 15003 | H21: =G21*(1+H41) -> 18003.6 | I21: =H21*(1+I41) -> 20704.14 | J21: =I21*(1+J41) -> 22774.554 | K21: =J21*(1+K41) -> 23913.282 | L21: =K21*(1+L41) -> 24630.68
C22: Passenger Ancillary | E22: 5306 | F22: 7892 | G22: 10504 | H22: =G22*(1+H42) -> 12604.8 | I22: =H22*(1+I42) -> 14495.52 | J22: =I22*(1+J42) -> 15945.072 | K22: =J22*(1+K42) -> 16742.326 | L22: =K22*(1+L42) -> 17244.595
C23: Affiliate Revenue | E23: 6920 | F23: 6977 | G23: 6977 | H23: 6977 | I23: 6977 | J23: 6977 | K23: 6977 | L23: 6977
C24: Advertising | E24: 2608 | F24: 5583 | G24: 5807 | H24: 5807 | I24: 5807 | J24: 5807 | K24: 5807 | L24: 5807
C25: Grants | E25: 1650 | F25: 2051 | G25: 2029 | H25: 2029 | I25: 2029 | J25: 2029 | K25: 2029 | L25: 2029
C26: Other Service Income | E26: 144 | F26: 457 | G26: 491 | H26: 491 | I26: 491 | J26: 491 | K26: 491 | L26: 491
C27: Total Ancillary Revenue | E27: =SUM(E21:E26) -> 22545 | F27: =SUM(F21:F26) -> 35455 | G27: =SUM(G21:G26) -> 40811 | H27: =SUM(H21:H26) -> 45912.4 | I27: =SUM(I21:I26) -> 50503.66 | J27: =SUM(J21:J26) -> 54023.626 | K27: =SUM(K21:K26) -> 55959.607 | L27: =SUM(L21:L26) -> 57179.276
C29: Total Revenue | E29: =SUM(E27,E19) -> 87662.79 | F29: =SUM(F27,F19) -> 187940.83 | G29: =SUM(G27,G19) -> 214034.07 | H29: =SUM(H27,H19) -> 243638.23 | I29: =SUM(I27,I19) -> 268748.32 | J29: =SUM(J27,J19) -> 286807.85 | K29: =SUM(K27,K19) -> 299055.97 | L29: =SUM(L27,L19) -> 311045.66
B31: x | C31: Growth Assumptions | E31: 2023 | F31: 2024 | G31: 2025 | H31: 2026 | I31: 2027 | J31: 2028 | K31: 2029 | L31: 2030
C33: Ridership
C34: Short-Distance | F34: =(F8-E8)/E8 -> -0.35030914 | G34: =(G8-F8)/F8 -> 0.080750855 | H34: =IF($E$44="Base Case",H49,IF($E$44="Best Case",H62,H75)) -> 0.18 | I34: =IF($E$44="Base Case",I49,IF($E$44="Best Case",I62,I75)) -> 0.14 | J34: =IF($E$44="Base Case",J49,IF($E$44="Best Case",J62,J75)) -> 0.105 | K34: =IF($E$44="Base Case",K49,IF($E$44="Best Case",K62,K75)) -> 0.03 | L34: =IF($E$44="Base Case",L49,IF($E$44="Best Case",L62,L75)) -> 0.03
C35: Long-Distance | F35: =(F9-E9)/E9 -> 4.3180077 | G35: =(G9-F9)/F9 -> 0.1603912 | H35: =IF($E$44="Base Case",H50,IF($E$44="Best Case",H63,H76)) -> 0.1 | I35: =IF($E$44="Base Case",I50,IF($E$44="Best Case",I63,I76)) -> 0.065 | J35: =IF($E$44="Base Case",J50,IF($E$44="Best Case",J63,J76)) -> 0.04 | K35: =IF($E$44="Base Case",K50,IF($E$44="Best Case",K63,K76)) -> 0.03 | L35: =IF($E$44="Base Case",L50,IF($E$44="Best Case",L63,L76)) -> 0.03
C37: Average Fare per Passenger
C38: Short-Distance | F38: =(F13-E13)/E13 -> 0.31510533 | G38: =(G13-F13)/F13 -> -0.11042945 | H38: =IF($E$44="Base Case",H53,IF($E$44="Best Case",H66,H79)) -> 0.04 | I38: =IF($E$44="Base Case",I53,IF($E$44="Best Case",I66,I79)) -> 0.03 | J38: =IF($E$44="Base Case",J53,IF($E$44="Best Case",J66,J79)) -> 0.02 | K38: =IF($E$44="Base Case",K53,IF($E$44="Best Case",K66,K79)) -> 0.01 | L38: =IF($E$44="Base Case",L53,IF($E$44="Best Case",L66,L79)) -> 0.01
C39: Long-Distance | F39: =(F14-E14)/E14 -> -0.14225451 | G39: =(G14-F14)/F14 -> 0.021038251 | H39: =IF($E$44="Base Case",H54,IF($E$44="Best Case",H67,H80)) -> 0.02 | I39: =IF($E$44="Base Case",I54,IF($E$44="Best Case",I67,I80)) -> 0.02 | J39: =IF($E$44="Base Case",J54,IF($E$44="Best Case",J67,J80)) -> 0.01 | K39: =IF($E$44="Base Case",K54,IF($E$44="Best Case",K67,K80)) -> 0.015 | L39: =IF($E$44="Base Case",L54,IF($E$44="Best Case",L67,L80)) -> 0.015
C41: Passenger Food and Beverage | F41: =(F21-E21)/E21 -> 1.111712 | G41: =(G21-F21)/F21 -> 0.20072029 | H41: =IF($E$44="Base Case",H56,IF($E$44="Best Case",H69,H82)) -> 0.2 | I41: =IF($E$44="Base Case",I56,IF($E$44="Best Case",I69,I82)) -> 0.15 | J41: =IF($E$44="Base Case",J56,IF($E$44="Best Case",J69,J82)) -> 0.1 | K41: =IF($E$44="Base Case",K56,IF($E$44="Best Case",K69,K82)) -> 0.05 | L41: =IF($E$44="Base Case",L56,IF($E$44="Best Case",L69,L82)) -> 0.03
C42: Passenger Ancillary | F42: =(F22-E22)/E22 -> 0.48737279 | G42: =(G22-F22)/F22 -> 0.33096807 | H42: =IF($E$44="Base Case",H57,IF($E$44="Best Case",H70,H83)) -> 0.2 | I42: =IF($E$44="Base Case",I57,IF($E$44="Best Case",I70,I83)) -> 0.15 | J42: =IF($E$44="Base Case",J57,IF($E$44="Best Case",J70,J83)) -> 0.1 | K42: =IF($E$44="Base Case",K57,IF($E$44="Best Case",K70,K83)) -> 0.05 | L42: =IF($E$44="Base Case",L57,IF($E$44="Best Case",L70,L83)) -> 0.03
B44: x | C44: Scenario | E44: Base Case
B46: x | C46: Base Case | E46: 2023 | F46: 2024 | G46: 2025 | H46: 2026 | I46: 2027 | J46: 2028 | K46: 2029 | L46: 2030
C48: Ridership
C49: Short-Distance | H49: 0.18 | I49: 0.14 | J49: 0.105 | K49: 0.03 | L49: 0.03
C50: Long-Distance | H50: 0.1 | I50: 0.065 | J50: 0.04 | K50: 0.03 | L50: 0.03
C52: Average Fare per Passenger
C53: Short-Distance | H53: 0.04 | I53: 0.03 | J53: 0.02 | K53: 0.01 | L53: 0.01
C54: Long-Distance | H54: 0.02 | I54: 0.02 | J54: 0.01 | K54: 0.015 | L54: 0.015
C56: Passenger Food and Beverage | H56: 0.2 | I56: 0.15 | J56: 0.1 | K56: 0.05 | L56: 0.03
C57: Passenger Ancillary | H57: 0.2 | I57: 0.15 | J57: 0.1 | K57: 0.05 | L57: 0.03
B59: x | C59: Best Case | E59: 2023 | F59: 2024 | G59: 2025 | H59: 2026 | I59: 2027 | J59: 2028 | K59: 2029 | L59: 2030
C61: Ridership
C62: Short-Distance | H62: 0.23 | I62: 0.19 | J62: 0.155 | K62: 0.06 | L62: 0.06
C63: Long-Distance | H63: 0.14 | I63: 0.115 | J63: 0.08 | K63: 0.05 | L63: 0.05
C65: Average Fare per Passenger
C66: Short-Distance | H66: 0.065 | I66: 0.055 | J66: 0.045 | K66: 0.03 | L66: 0.03
C67: Long-Distance | H67: 0.045 | I67: 0.045 | J67: 0.035 | K67: 0.03 | L67: 0.03
C69: Passenger Food and Beverage | H69: 0.25 | I69: 0.2 | J69: 0.15 | K69: 0.08 | L69: 0.06
C70: Passenger Ancillary | H70: 0.25 | I70: 0.2 | J70: 0.15 | K70: 0.08 | L70: 0.06
B72: x | C72: Weak Case | E72: 2023 | F72: 2024 | G72: 2025 | H72: 2026 | I72: 2027 | J72: 2028 | K72: 2029 | L72: 2030
C74: Ridership
C75: Short-Distance | H75: 0.13 | I75: 0.09 | J75: 0.055 | K75: 0 | L75: 0
C76: Long-Distance | H76: 0.03 | I76: 0.015 | J76: 0 | K76: 0 | L76: 0
C78: Average Fare per Passenger
C79: Short-Distance | H79: 0.015 | I79: 0.005 | J79: -0.005 | K79: -0.015 | L79: -0.015
C80: Long-Distance | H80: 0 | I80: 0 | J80: -0.01 | K80: -0.015 | L80: -0.015
C82: Passenger Food and Beverage | H82: 0.15 | I82: 0.1 | J82: 0.05 | K82: 0 | L82: 0
C83: Passenger Ancillary | H83: 0.15 | I83: 0.1 | J83: 0.05 | K83: 0 | L83: 0
B85: x | C85: Operating Expenses Forecast Model
C87: Periods | E87: 2023 | F87: 2024 | G87: 2025 | H87: 2026 | I87: 2027 | J87: 2028 | K87: 2029 | L87: 2030
C89: Labour | E89: 28732 | F89: 39110 | G89: 39018 | H89: =G89*(1+H104) -> 42919.8 | I89: =H89*(1+I104) -> 46138.785 | J89: =I89*(1+J104) -> 49137.806 | K89: =J89*(1+K104) -> 51840.385 | L89: =K89*(1+L104) -> 54691.607
C90: Maintenance of Way | E90: 13979 | F90: 32467 | G90: 33440 | H90: =G90*(1+H105) -> 34443.2 | I90: =H90*(1+I105) -> 35476.496 | J90: =I90*(1+J105) -> 36540.791 | K90: =J90*(1+K105) -> 38002.423 | L90: =K90*(1+L105) -> 39522.519
C91: Maintenance of Equipment | E91: 11050 | F91: 14859 | G91: 16491 | H91: =G91*(1+H106) -> 17398.005 | I91: =H91*(1+I106) -> 17919.945 | J91: =I91*(1+J106) -> 18457.544 | K91: =J91*(1+K106) -> 19195.845 | L91: =K91*(1+L106) -> 19963.679
C92: Fuel | E92: 7806 | F92: 14027 | G92: 14305 | H92: =G92*(1+H107) -> 20027 | I92: =H92*(1+I107) -> 18024.3 | J92: =I92*(1+J107) -> 16221.87 | K92: =J92*(1+K107) -> 16708.526 | L92: =K92*(1+L107) -> 17209.782
C93: Facilities and Others | E93: 43793 | F93: 56754 | G93: 38506 | H93: =G93*(1+H108) -> 38506 | I93: =H93*(1+I108) -> 38506 | J93: =I93*(1+J108) -> 38506 | K93: =J93*(1+K108) -> 38506 | L93: =K93*(1+L108) -> 38506
C94: Train Operating Expenses | E94: =SUM(E89:E93) -> 105360 | F94: =SUM(F89:F93) -> 157217 | G94: =SUM(G89:G93) -> 141760 | H94: =SUM(H89:H93) -> 153294.01 | I94: =SUM(I89:I93) -> 156065.53 | J94: =SUM(J89:J93) -> 158864.01 | K94: =SUM(K89:K93) -> 164253.18 | L94: =SUM(L89:L93) -> 169893.59
C96: Corporate, G&A | E96: 48871 | F96: 58672 | G96: 58950 | H96: 58950 | I96: 58950 | J96: 58950 | K96: 58950 | L96: 58950
C97: Expansion Costs | E97: 19520 | F97: 43 | G97: 62 | H97: =AVERAGE($F$97:$G$97) -> 52.5 | I97: =AVERAGE($F$97:$G$97) -> 52.5 | J97: =AVERAGE($F$97:$G$97) -> 52.5 | K97: =AVERAGE($F$97:$G$97) -> 52.5 | L97: =AVERAGE($F$97:$G$97) -> 52.5
C98: Other Expenses | E98: =SUM(E96:E97) -> 68391 | F98: =SUM(F96:F97) -> 58715 | G98: =SUM(G96:G97) -> 59012 | H98: =SUM(H96:H97) -> 59002.5 | I98: =SUM(I96:I97) -> 59002.5 | J98: =SUM(J96:J97) -> 59002.5 | K98: =SUM(K96:K97) -> 59002.5 | L98: =SUM(L96:L97) -> 59002.5
C100: Total Operating Expenses | E100: =SUM(E98,E94) -> 173751 | F100: =SUM(F98,F94) -> 215932 | G100: =SUM(G98,G94) -> 200772 | H100: =SUM(H98,H94) -> 212296.51 | I100: =SUM(I98,I94) -> 215068.03 | J100: =SUM(J98,J94) -> 217866.51 | K100: =SUM(K98,K94) -> 223255.68 | L100: =SUM(L98,L94) -> 228896.09
B102: x | C102: Growth Assumptions | E102: 2023 | F102: 2024 | G102: 2025 | H102: 2026 | I102: 2027 | J102: 2028 | K102: 2029 | L102: 2030
C104: Labour | F104: =(F89-E89)/E89 -> 0.36120006 | G104: =(G89-F89)/F89 -> -0.0023523396 | H104: 0.1 | I104: 0.075 | J104: 0.065 | K104: 0.055 | L104: 0.055
C105: Maintenance of Way | F105: =(F90-E90)/E90 -> 1.3225553 | G105: =(G90-F90)/F90 -> 0.029968891 | H105: 0.03 | I105: 0.03 | J105: 0.03 | K105: 0.04 | L105: 0.04
C106: Maintenance of Equipment | F106: =(F91-E91)/E91 -> 0.34470588 | G106: =(G91-F91)/F91 -> 0.10983242 | H106: 0.055 | I106: 0.03 | J106: 0.03 | K106: 0.04 | L106: 0.04
C107: Fuel | F107: =(F92-E92)/E92 -> 0.79695106 | G107: =(G92-F92)/F92 -> 0.019818921 | H107: 0.4 | I107: -0.1 | J107: -0.1 | K107: 0.03 | L107: 0.03
C108: Facilities and Others | F108: =(F93-E93)/E93 -> 0.29596054 | G108: =(G93-F93)/F93 -> -0.321528 | H108: 0 | I108: 0 | J108: 0 | K108: 0 | L108: 0
B110: x | C110: Simplified Cash Calculation
C112: Periods | E112: 2023 | F112: 2024 | G112: 2025 | H112: 2026 | I112: 2027 | J112: 2028 | K112: 2029 | L112: 2030
C114: Revenue | E114: ='Brightline DCF Valuation'!E29 -> 87662.79 | F114: ='Brightline DCF Valuation'!F29 -> 187940.83 | G114: ='Brightline DCF Valuation'!G29 -> 214034.07 | H114: ='Brightline DCF Valuation'!H29 -> 243638.23 | I114: ='Brightline DCF Valuation'!I29 -> 268748.32 | J114: ='Brightline DCF Valuation'!J29 -> 286807.85 | K114: ='Brightline DCF Valuation'!K29 -> 299055.97 | L114: ='Brightline DCF Valuation'!L29 -> 311045.66
C115: Operating Expenses | E115: =-'Brightline DCF Valuation'!E100 -> -173751 | F115: =-'Brightline DCF Valuation'!F100 -> -215932 | G115: =-'Brightline DCF Valuation'!G100 -> -200772 | H115: =-'Brightline DCF Valuation'!H100 -> -212296.51 | I115: =-'Brightline DCF Valuation'!I100 -> -215068.03 | J115: =-'Brightline DCF Valuation'!J100 -> -217866.51 | K115: =-'Brightline DCF Valuation'!K100 -> -223255.68 | L115: =-'Brightline DCF Valuation'!L100 -> -228896.09
C116: EBITDA | E116: =SUM(E114:E115) -> -86088.21 | F116: =SUM(F114:F115) -> -27991.171 | G116: =SUM(G114:G115) -> 13262.07 | H116: =SUM(H114:H115) -> 31341.722 | I116: =SUM(I114:I115) -> 53680.29 | J116: =SUM(J114:J115) -> 68941.34 | K116: =SUM(K114:K115) -> 75800.29 | L116: =SUM(L114:L115) -> 82149.577
C118: CapEx (Net of asset sales/grants) | E118: -469519 | F118: -252324 | G118: -50207 | H118: -20000 | I118: -20000 | J118: -20000 | K118: -20000 | L118: -20000
C119: Changes in Working Capital | E119: 136344 | F119: -3860 | G119: -36385 | H119: -5000 | I119: -5000 | J119: -5000 | K119: -5000 | L119: -5000
C120: Unlevered Free Cash | E120: =SUM(E116,E118,E119) -> -419263.21 | F120: =SUM(F116,F118,F119) -> -284175.17 | G120: =SUM(G116,G118,G119) -> -73329.93 | H120: =SUM(H116,H118,H119) -> 6341.722 | I120: =SUM(I116,I118,I119) -> 28680.29 | J120: =SUM(J116,J118,J119) -> 43941.34 | K120: =SUM(K116,K118,K119) -> 50800.29 | L120: =SUM(L116,L118,L119) -> 57149.577
C121: Present Value of UFCF | H121: =(H120/((1+$E$132)^(H112-$G$112))) -> 5687.643 | I121: =(I120/((1+$E$132)^(I112-$G$112))) -> 23069.267 | J121: =(J120/((1+$E$132)^(J112-$G$112))) -> 31699.229 | K121: =(K120/((1+$E$132)^(K112-$G$112))) -> 32867.504 | L121: =(L120/((1+$E$132)^(L112-$G$112))) -> 33161.845
B123: x | C123: WACC
C125: Cost of Equity
C126: Risk-Free Rate | E126: 0.044
C127: Risk Premium | E127: 0.057
C128: Unlevered Beta | E128: 0.72
C129: Total | E129: =ROUND(E126+(E127*E128),3) -> 0.085
C131: Distress Premium | E131: 0.03
C132: Total Discount Rate (r) | E132: =SUM(E131,E129) -> 0.115
B134: x | C134: Terminal Value | G134: Sensitivity (G/r)
G135: =E140 -> 528329.02 | H135: 0.095 | I135: 0.105 | J135: 0.115 | K135: 0.125 | L135: 0.135
C136: GGM Growth Rate (G) | E136: 0.03 | G136: 0.02 | H136: 628538.36 | I136: 546836.23 | J136: 482538.98 | K136: 430666.21 | L136: 387970.17
G137: 0.025 | H137: 666397.2 | I137: 575021.68 | J137: 504162.06 | K137: 447655.83 | L137: 401581.77
C138: Present Value of UFCF | E138: =SUM(H121:L121) -> 126485.49 | G138: 0.03 | H138: 710080.47 | I138: 606965.19 | J138: 528329.02 | K138: 466433.83 | L138: 416489.71
C139: Present Value of TV | E139: =(((L120*(1+E136))/(E132-E136)))/((1+E132)^(L112-G112)) -> 401843.54 | G139: 0.035 | H139: 761044.29 | I139: 643472.06 | J139: 555516.86 | K139: 487298.28 | L139: 432888.44
C140: Total Enterprise Value | E140: =SUM(E138:E139) -> 528329.02 | G140: 0.04 | H140: 821274.25 | I140: 685595.37 | J140: 586329.74 | K140: 510617.36 | L140: 451013.36
